keystone/hexagon_const.py
keystone/arm64_const.py
keystone/ppc_const.py
keystone/evm_const.py
keystone/x86_const.py
keystone/libkeystone.so
keystone/sparc_const.py
keystone/__init__.py
keystone/keystone_const.py
keystone/keystone.py
keystone/systemz_const.py
keystone/mips_const.py
keystone/arm_const.py
keystone_engine-0.9.2.dist-info/RECORD
keystone_engine-0.9.2.dist-info/WHEEL
keystone_engine-0.9.2.dist-info/METADATA
keystone_engine-0.9.2.dist-info/LICENSE.TXT
keystone_engine-0.9.2.dist-info/zip-safe
keystone_engine-0.9.2.dist-info/top_level.txt
